llm_catcher/__init__.py
llm_catcher/diagnoser.py
llm_catcher/settings.py
llm_catcher-0.4.0.dist-info/LICENSE
llm_catcher-0.4.0.dist-info/METADATA
llm_catcher-0.4.0.dist-info/WHEEL
llm_catcher-0.4.0.dist-info/top_level.txt
llm_catcher-0.4.0.dist-info/RECORD
