Metadata-Version: 2.1
Name: llm-catcher
Version: 0.4.0
Summary: A Python library that uses LLMs to diagnose and explain exceptions
Author: Dave York
Author-email: Dave York <dave.york@me.com>
License:                     GNU GENERAL PUBLIC LICENSE
Requires-Python: >=3.8
License-File: LICENSE
Requires-Dist: pydantic>=2.0.0
Requires-Dist: pydantic-settings>=2.0.0
Requires-Dist: openai>=1.0.0
Requires-Dist: python-dotenv>=0.19.0
Requires-Dist: loguru>=0.6.0
Requires-Dist: ollama==0.4.5
Provides-Extra: dev
Requires-Dist: pytest>=7.4.0; extra == "dev"
Requires-Dist: flake8>=6.1.0; extra == "dev"
Requires-Dist: pytest-asyncio>=0.21.1; extra == "dev"
Provides-Extra: fastapi
Requires-Dist: fastapi>=0.68.0; extra == "fastapi"
Requires-Dist: uvicorn>=0.15.0; extra == "fastapi"
Requires-Dist: requests>=2.26.0; extra == "fastapi"
